pitop/miniscreen/__init__.py
pitop/miniscreen/miniscreen.py
pitop/miniscreen/buttons/__init__.py
pitop/miniscreen/buttons/buttons.py
pitop/miniscreen/images/rocket.gif
pitop/miniscreen/oled/__init__.py
pitop/miniscreen/oled/assistant.py
pitop/miniscreen/oled/oled.py
pitop/miniscreen/oled/core/__init__.py
pitop/miniscreen/oled/core/canvas.py
pitop/miniscreen/oled/core/device_controller.py
pitop/miniscreen/oled/core/fps_regulator.py
pitop/miniscreen/oled/core/lock.py
pitop/miniscreen/oled/core/contrib/__init__.py
pitop/miniscreen/oled/core/contrib/luma/LICENSE.rst
pitop/miniscreen/oled/core/contrib/luma/README.md
pitop/miniscreen/oled/core/contrib/luma/__init__.py
pitop/miniscreen/oled/core/contrib/luma/core/__init__.py
pitop/miniscreen/oled/core/contrib/luma/core/const.py
pitop/miniscreen/oled/core/contrib/luma/core/device.py
pitop/miniscreen/oled/core/contrib/luma/core/error.py
pitop/miniscreen/oled/core/contrib/luma/core/mixin.py
pitop/miniscreen/oled/core/contrib/luma/core/threadpool.py
pitop/miniscreen/oled/core/contrib/luma/core/virtual.py
pitop/miniscreen/oled/core/contrib/luma/core/interface/__init__.py
pitop/miniscreen/oled/core/contrib/luma/core/interface/serial.py
pitop/miniscreen/oled/core/contrib/luma/oled/__init__.py
pitop/miniscreen/oled/core/contrib/luma/oled/const.py
pitop/miniscreen/oled/core/contrib/luma/oled/device/__init__.py
pitop.miniscreen-0.34.3.post1.dist-info/METADATA
pitop.miniscreen-0.34.3.post1.dist-info/WHEEL
pitop.miniscreen-0.34.3.post1.dist-info/top_level.txt
pitop.miniscreen-0.34.3.post1.dist-info/RECORD
